hymath
