Metadata-Version: 1.1
Name: hymath
Version: 0.0.8
Summary: 学而思火焰工作室数学库
Home-page: https://github.com/
Author: Dingdang Wang
Author-email: 1330274738@qq.com
License: UNKNOWN
Platform: UNKNOWN
Classifier: Programming Language :: Python :: 3
Classifier: License :: OSI Approved :: MIT License
Classifier: Operating System :: OS Independent
